[
    {
        "itens": [
            {
                "tipo": "normal",
                "codigo": "107",
                "quantidade": 1,
                "observacao": [
                    "Ao ponto",
                    "Sem picles",
                    "test comments"
                ]
            }
        ],
        "observacao": "6554731"
    },
    {
        "itens": [
            {
                "tipo": "normal",
                "codigo": "107",
                "quantidade": 1,
                "observacao": [
                    "Ao ponto",
                    "Sem picles",
                    "test comments"
                ]
            }
        ],
        "observacao": "6554731"
    },
    {
        "itens": [
            {
                "tipo": "normal",
                "codigo": "107",
                "quantidade": 1,
                "observacao": [
                    "Ao ponto",
                    "Sem picles",
                    "test comments"
                ]
            }
        ],
        "observacao": "6554732"
    }
]
